optionc/__init__.py
optionc/decorators.py
optionc/nil.py
optionc/option.py
optionc/some.py
optionc/utils.py
optionc-0.1.0.dist-info/METADATA
optionc-0.1.0.dist-info/WHEEL
optionc-0.1.0.dist-info/licenses/LICENSE
optionc-0.1.0.dist-info/RECORD
