Metadata-Version: 2.4
Name: optionc
Version: 0.1.0
Summary: Scala-inspired Option type for Python with functional programming utilities
Project-URL: Homepage, https://github.com/your-username/optionc
Project-URL: Repository, https://github.com/your-username/optionc.git
Project-URL: Issues, https://github.com/your-username/optionc/issues
Author: Carl You
License: MIT
License-File: LICENSE
Keywords: functional,maybe,monads,option,programming,scala
Classifier: Development Status :: 4 - Beta
Classifier: Intended Audience :: Developers
Classifier: License :: OSI Approved :: MIT License
Classifier: Programming Language :: Python :: 3
Classifier: Programming Language :: Python :: 3.10
Classifier: Programming Language :: Python :: 3.11
Classifier: Programming Language :: Python :: 3.12
Classifier: Topic :: Software Development :: Libraries :: Python Modules
Classifier: Typing :: Typed
Requires-Python: >=3.10
Provides-Extra: dev
Requires-Dist: pytest-cov>=4.0.0; extra == 'dev'
Requires-Dist: pytest>=7.0.0; extra == 'dev'
Provides-Extra: underscorec
Requires-Dist: underscorec; extra == 'underscorec'
